MANIFEST.in
README.rst
setup.py
krinker/__init__.py
krinker/text.py
krinker.egg-info/PKG-INFO
krinker.egg-info/SOURCES.txt
krinker.egg-info/dependency_links.txt
krinker.egg-info/not-zip-safe
krinker.egg-info/top_level.txt