Metadata-Version: 1.0
Name: krinker
Version: 0.2
Summary: Testing python's distribute
Home-page: http://al-krinker.blogspot.com/
Author: Al Krinker
Author-email: al.krinker@gmail.com
License: MIT
Platform: UNKNOWN
